voter.v
module voter_if (I, O);
input [3:0] I;  //宣告四人投票輸入I
output [3:1] O; //宣告三種結果輸出O
reg [3:1] O;

always@ (I)
begin
    case (I)
        //O3(反對)
        4'b0000, 4'b0001, 4'b0010, 4'b0100, 4'b1000:
            O = 3'b001;

        //O2(平手)
        4'b0011, 4'b0101, 4'b0110, 4'b1001, 4'b1010, 4'b1100:
            O = 3'b010;

        //O1(贊成)
        4'b1110, 4'b1101, 4'b1011, 4'b0111, 4'b1111:
            O = 3'b100;

        default:
            O = 3'b000;
    endcase
end
endmodule

voter_tb.v
`include "voter.v"
module voter_tb;
reg [3:0] IN;
wire [3:1] OUT;
voter_if v( IN, OUT );
initial
begin
    $dumpfile("voter.vcd");
    $dumpvars(0, v);
    #0  IN[3:0] = 4'b0000;
    #10 IN[3:0] = 4'b0001;
    #10 IN[3:0] = 4'b0010;
    #10 IN[3:0] = 4'b0011;
    #10 IN[3:0] = 4'b0100;
    #10 IN[3:0] = 4'b0101;
    #10 IN[3:0] = 4'b0110;
    #10 IN[3:0] = 4'b0111;
    #10 IN[3:0] = 4'b1000;
    #10 IN[3:0] = 4'b1001;
    #10 IN[3:0] = 4'b1010;
    #10 IN[3:0] = 4'b1011;
    #10 IN[3:0] = 4'b1100;
    #10 IN[3:0] = 4'b1101;
    #10 IN[3:0] = 4'b1110;
    #10 IN[3:0] = 4'b1111;
    #10 $finish;
end
endmodule

voter.vcd
$date
	Fri Apr 08 15:14:06 2022
$end
$version
	Icarus Verilog
$end
$timescale
	1s
$end
$scope module voter_tb $end
$scope module v $end
$var wire 4 ! I [3:0] $end
$var reg 3 " O [3:1] $end
$upscope $end
$upscope $end
$enddefinitions $end
#0
$dumpvars
b1 "
b0 !
$end
#10
b1 !
#20
b10 !
#30
b10 "
b11 !
#40
b1 "
b100 !
#50
b10 "
b101 !
#60
b110 !
#70
b100 "
b111 !
#80
b1 "
b1000 !
#90
b10 "
b1001 !
#100
b1010 !
#110
b100 "
b1011 !
#120
b10 "
b1100 !
#130
b100 "
b1101 !
#140
b1110 !
#150
b1111 !
